{"meta":{"formatVersion":1,"source":"ai"},"project":{"name":"CS25MMSCFD","datesaved":"","timesaved":"","startup":"","markerLabel":""},"scopes":{"scopeId":["S001","S002","S003","S004","S005","S006","S007","S008","S009","S010","S011","S012","S013","S014","S015","S016","S017","S018","S019","S020","S021","S022","S023","S024"],"label":["Mobilization & Site Setup","Clearing/Grading & Earthwork","Roads/Drainage/Fencing","Concrete Foundations & Equipment Pads","Structural Steel & Pipe Supports","Set Slug Catcher","Install Suction Metering Skid/Run","Install 20in Suction Header Piping","Set CAT 3516 Compressors (Qty 5)","Install Discharge Header Piping","Set Filter Separator","Set Glycol Dehy Tower","Install Glycol System Piping & Reboiler","Set Fuel Gas Supply Skid","Set Instrument Air Skid","Set Condensate Tanks (Qty 4)","Set Water Bullet Tank","Set VRUs (Qty 2)","Install Vent Stack & Separator","Set PDC/Control Building","Electrical Grounding/Conduit/Cable Tray","Electrical Cable Pull/Terminate/Power-Up","Instrumentation Install & Tubing/Hookup","Pre-Commissioning, Commissioning & Demobilization"],"start":["","","","","","","","","","","","","","","","","","","","","","","","",""],"end":["","","","","","","","","","","","","","","","","","","","","","","","",""],"cost":[2,4,4,8,4,4,3,5,18,6,3,4,4,2,2,3,2,3,2,4,7,6,6,4],"progressValue":["","","","","","","","","","","","","","","","","","","","","","","","",""],"unitsToDate":["","","","","","","","","","","","","","","","","","","","","","","","",""],"totalUnits":["","","","","","","","","","","","","","","","","","","","","","","","",""],"unitsLabel":["%","%","%","Each","Tons","Each","Each","Feet","Each","Feet","Each","Each","%","Each","Each","Each","Each","Each","Each","Each","Feet","Feet","Feet","%"],"sectionName":["Site-Civil","Site-Civil","Site-Civil","Foundations-Structural","Foundations-Structural","Mechanical-Process","Mechanical-Process","Mechanical-Process","Mechanical-Process","Mechanical-Process","Mechanical-Process","Mechanical-Process","Mechanical-Process","Mechanical-Process","Mechanical-Process","Mechanical-Process","Mechanical-Process","Mechanical-Process","Mechanical-Process","Electrical-IE","Electrical-IE","Electrical-IE","Electrical-IE","Commissioning-Closeout"],"sectionID":["SEC1","SEC1","SEC1","SEC2","SEC2","SEC3","SEC3","SEC3","SEC3","SEC3","SEC3","SEC3","SEC3","SEC3","SEC3","SEC3","SEC3","SEC3","SEC3","SEC4","SEC4","SEC4","SEC4","SEC5"]},"timeseries":{"project":{"date":[],"baselinePct":[],"plannedPct":[],"dailyActual":[],"actualPct":[]},"scopes":{"historyDate":[],"scopeId":[],"label":[],"start":[],"end":[],"cost":[],"perDay":[],"actualPct":[],"unitsToDate":[],"totalUnits":[],"unitsLabel":[],"plannedtodate":[],"sectionName":[],"sectionID":[]},"sections":{"historyDate":[],"sectionID":[],"sectionTitle":[],"sectionWeight":[],"sectionPct":[],"sectionPlannedPct":[]},"projectMeta":{"historyDate":[],"key":[],"value":[]}}}
